{
  "name": "threejs-exporters",
  "description": "Three.js exporters",
  "keywords": [
    "threejs",
    "exporters",
    "three.js"
  ],
  "license": "MIT",
  "homepage": "https://github.com/Tomesch/threejs-exporters",
  "_release": "3a9bdc8f3d",
  "_resolution": {
    "type": "branch",
    "branch": "master",
    "commit": "3a9bdc8f3d4af39440c709b7d665c6456ed4dc45"
  },
  "_source": "git://github.com/Tomesch/threejs-exporters.git",
  "_target": "*",
  "_originalSource": "threejs-exporters"
}